examples/__init__.py
examples/content_migration.py
examples/example_usage.py
examples/generate_embed_url.py
examples/model.py
examples/query.py
examples/snowflake_semantic_view.py
examples/topic.py
examples/tests/__init__.py
examples/tests/test_snowflake_semantic_view.py
examples/tests/test_topic.py
omni_python_sdk/__init__.py
omni_python_sdk/api.py
omni_python_sdk-0.1.11.dist-info/licenses/LICENSE
omni_python_sdk-0.1.11.dist-info/METADATA
omni_python_sdk-0.1.11.dist-info/WHEEL
omni_python_sdk-0.1.11.dist-info/top_level.txt
omni_python_sdk-0.1.11.dist-info/RECORD
