Metadata-Version: 2.4
Name: omni_python_sdk
Version: 0.1.11
Summary: A Python SDK for Omni API
Home-page: https://github.com/exploreomni/omni-python-sdk
Author: Jamie Davidson
Author-email: jamie@omni.co
Classifier: Programming Language :: Python :: 3
Classifier: License :: OSI Approved :: MIT License
Classifier: Operating System :: OS Independent
Requires-Python: >=3.9
License-File: LICENSE
Requires-Dist: requests
Requires-Dist: pyarrow
Requires-Dist: ndjson
Requires-Dist: dotenv
Dynamic: author
Dynamic: author-email
Dynamic: classifier
Dynamic: description
Dynamic: description-content-type
Dynamic: home-page
Dynamic: license-file
Dynamic: requires-dist
Dynamic: requires-python
Dynamic: summary
